odoo/addons/purchase_order_line_menu/README.rst
odoo/addons/purchase_order_line_menu/__init__.py
odoo/addons/purchase_order_line_menu/__manifest__.py
odoo/addons/purchase_order_line_menu/i18n/es.po
odoo/addons/purchase_order_line_menu/i18n/fr_FR.po
odoo/addons/purchase_order_line_menu/i18n/hr.po
odoo/addons/purchase_order_line_menu/i18n/it.po
odoo/addons/purchase_order_line_menu/i18n/ja.po
odoo/addons/purchase_order_line_menu/i18n/pt_BR.po
odoo/addons/purchase_order_line_menu/i18n/purchase_order_line_menu.pot
odoo/addons/purchase_order_line_menu/models/__init__.py
odoo/addons/purchase_order_line_menu/models/purchase_order_line.py
odoo/addons/purchase_order_line_menu/readme/CONTRIBUTORS.md
odoo/addons/purchase_order_line_menu/readme/DESCRIPTION.md
odoo/addons/purchase_order_line_menu/readme/USAGE.md
odoo/addons/purchase_order_line_menu/static/description/icon.png
odoo/addons/purchase_order_line_menu/static/description/index.html
odoo/addons/purchase_order_line_menu/views/purchase_order_line_views.xml
odoo_addon_purchase_order_line_menu-18.0.1.0.2.2.dist-info/METADATA
odoo_addon_purchase_order_line_menu-18.0.1.0.2.2.dist-info/WHEEL
odoo_addon_purchase_order_line_menu-18.0.1.0.2.2.dist-info/top_level.txt
odoo_addon_purchase_order_line_menu-18.0.1.0.2.2.dist-info/RECORD
