Metadata-Version: 2.1
Name: odoo-addon-purchase_order_line_menu
Version: 18.0.1.0.2.2
Requires-Python: >=3.10
Requires-Dist: odoo==18.0.*
Summary: Adds Purchase Order Lines Menu
Home-page: https://github.com/OCA/purchase-workflow
License: AGPL-3
Author: Open Source Integrators, Odoo Community Association (OCA)
Author-email: support@odoo-community.org
Classifier: Programming Language :: Python
Classifier: Framework :: Odoo
Classifier: Framework :: Odoo :: 18.0
Classifier: License :: OSI Approved :: GNU Affero General Public License v3
Classifier: Development Status :: 5 - Production/Stable
